mcp/mipsmulti.v
//-------------------------------------------------------
// mipsmulti.v
// From David_Harris and Sarah_Harris book design
// Multicycle MIPS processor
//------------------------------------------------

module mips(input         clk, reset,
            output [31:0] adr, writedata,
            output        memwrite,
            input  [31:0] readdata);

  wire        zero, pcen, irwrite, regwrite;
  wire        alusrca, iord, memtoreg, regdst;
  wire [1:0]  alusrcb, pcsrc;
  wire [2:0]  alucontrol;
  wire [5:0]  op, funct;

  controller c(clk, reset, op, funct, zero,
               pcen, memwrite, irwrite, regwrite,
               alusrca, iord, memtoreg, regdst,
               alusrcb, pcsrc, alucontrol);
  datapath dp(clk, reset,
              pcen, irwrite, regwrite,
              alusrca, iord, memtoreg, regdst,
              alusrcb, pcsrc, alucontrol,
              op, funct, zero,
              adr, writedata, readdata);
endmodule

module controller(input        clk, reset,
                  input  [5:0] op, funct,
                  input        zero,
                  output       pcen, memwrite, irwrite, regwrite,
                  output       alusrca, iord, memtoreg, regdst,
                  output [1:0] alusrcb, pcsrc,
                  output [2:0] alucontrol);

  wire [1:0] aluop;
  wire       branch, pcwrite;

  // Main Decoder and ALU Decoder subunits.
  maindec md(clk, reset, op,
             pcwrite, memwrite, irwrite, regwrite,
             alusrca, branch, iord, memtoreg, regdst,
             alusrcb, pcsrc, aluop);
  aludec  ad(funct, aluop, alucontrol);

  assign pcen = (branch & zero) | pcwrite;
endmodule

module maindec(input        clk, reset,
               input  [5:0] op,
               output       pcwrite, memwrite, irwrite, regwrite,
               output       alusrca, branch, iord, memtoreg, regdst,
               output [1:0] alusrcb, pcsrc,
               output [1:0] aluop);

  // This is a moore machine.
  parameter   FETCH   = 4'b0000; // State 0
  parameter   DECODE  = 4'b0001; // State 1
  parameter   MEMADR  = 4'b0010;	// State 2
  parameter   MEMRD   = 4'b0011;	// State 3
  parameter   MEMWB   = 4'b0100;	// State 4
  parameter   MEMWR   = 4'b0101;	// State 5
  parameter   RTYPEEX = 4'b0110;	// State 6
  parameter   RTYPEWB = 4'b0111;	// State 7
  parameter   BEQEX   = 4'b1000;	// State 8
  parameter   ADDIEX  = 4'b1001;	// State 9
  parameter   ADDIWB  = 4'b1010;	// state 10
  parameter   JEX     = 4'b1011;	// State 11

  parameter   LW      = 6'b100011;	// Opcode for lw
  parameter   SW      = 6'b101011;	// Opcode for sw
  parameter   RTYPE   = 6'b000000;	// Opcode for R-type
  parameter   BEQ     = 6'b000100;	// Opcode for beq
  parameter   ADDI    = 6'b001000;	// Opcode for addi
  parameter   J       = 6'b000010;	// Opcode for j

  reg [3:0]  state, nextstate;
  reg [14:0] controls;

  // state register
  always @(posedge clk or posedge reset)
    if(reset) state <= FETCH;
    else state <= nextstate;

  // next state logic
  always @ (*)
    case(state)
      FETCH:   nextstate <= DECODE;
      DECODE:  case(op)
                 LW:      nextstate <= MEMADR;
                 SW:      nextstate <= MEMADR;
                 RTYPE:   nextstate <= RTYPEEX;
                 BEQ:     nextstate <= BEQEX;
                 ADDI:    nextstate <= ADDIEX;
                 J:       nextstate <= JEX;
                 default: nextstate <= 4'bx; // should never happen
               endcase
      MEMADR: case(op)
                LW: nextstate <= MEMRD;
                SW: nextstate <= MEMWR;
                default: nextstate <= 4'bx; // should never happen
              endcase
      MEMRD: nextstate <= MEMWB;
      MEMWB: nextstate <= FETCH;
      MEMWR: nextstate <= FETCH;
      RTYPEEX: nextstate <= RTYPEWB;
      RTYPEWB: nextstate <= FETCH;
      BEQEX: nextstate <= FETCH;
      ADDIEX: nextstate <= ADDIWB;
      ADDIWB: nextstate <= FETCH;
      JEX: nextstate <= FETCH;
      default: nextstate <= 4'bx; // should never happen
    endcase

  // output logic
  assign {pcwrite, memwrite, irwrite, regwrite, alusrca, branch, iord, memtoreg, regdst, alusrcb, pcsrc, aluop} = controls;

  always @ (*)
    case(state)
      FETCH:    controls <= 15'h5010;
      DECODE:   controls <= 15'h0030;
      MEMADR:   controls <= 15'h0420;
      MEMRD:    controls <= 15'h0100;
      MEMWB:    controls <= 15'h0880;
      MEMWR:    controls <= 15'h2100;
      RTYPEEX:  controls <= 15'h0402;
      RTYPEWB:  controls <= 15'h0840;
      BEQEX:    controls <= 15'h0605;
      ADDIEX:   controls <= 15'h0420;
      ADDIWB:   controls <= 15'h1000;
      JEX:      controls <= 15'h4008;
      default: controls <= 15'hxxxx; // should never happen
    endcase
  // assign {pcwrite, memwrite, irwrite, regwrite, alusrca, branch, iord, memtoreg, regdst, alusrcb, pcsrc, aluop} = controls;
endmodule

module aludec(input  [5:0] funct,
              input  [1:0] aluop,
              output reg [2:0] alucontrol);

always@(*)
    case(aluop)
    2'b00:  alucontrol <= 3'b010; // add
    2'b01:  alucontrol <= 3'b110; // sub
    default: case(funct)
        6'b100000: alucontrol <= 3'b010; // add
        6'b100010: alucontrol <= 3'b110; // sub
        6'b100100: alucontrol <= 3'b000; // and
        6'b100101: alucontrol <= 3'b001; // or
        6'b101010: alucontrol <= 3'b111; // slt
        default:   alucontrol <= 3'bxxx; // ???
      endcase
    endcase
endmodule




// Complete the datapath module below for Lab 11.
// You do not need to complete this module for Lab 10

// The datapath unit is a structural verilog module.  That is,
// it is composed of instances of its sub-modules.  For example,
// the instruction register is instantiated as a 32-bit flopenr.
// The other submodules are likewise instantiated.

module datapath(input         clk, reset,
                input         pcen, irwrite, regwrite,
                input         alusrca, iord, memtoreg, regdst,
                input  [1:0]  alusrcb, pcsrc,
                input  [2:0]  alucontrol,
                output [5:0]  op, funct,
                output        zero,
                output [31:0] adr, writedata,
                input  [31:0] readdata);

  // Below are the internal signals of the datapath module.

  wire [4:0]  writereg;
  wire [31:0] pcnext, pc;
  wire [31:0] instr, data, srca, srcb;
  wire [31:0] a;
  wire [31:0] aluresult, aluout;
  wire [31:0] signimm;   // the sign-extended immediate
  wire [31:0] signimmsh;	// the sign-extended immediate shifted left by 2
  wire [31:0] wd3, rd1, rd2;

  // op and funct fields to controller
  assign op = instr[31:26];
  assign funct = instr[5:0];

  // Your datapath hardware goes below.  Instantiate each of the submodules
  // that you need.  Remember that alu's, mux's and various other
  // versions of parameterizable modules are available in mipsparts.sv
  // from Lab 9. You'll likely want to include this verilog file in your
  // simulation.

  // We've included parameterizable 3:1 and 4:1 muxes below for your use.

  // Remember to give your instantiated modules applicable names
  // such as pcreg (PC register), wdmux (Write Data Mux), etc.
  // so it's easier to understand.

  // ADD CODE HERE

  // datapath

endmodule


module mux3 #(parameter WIDTH = 8)
             (input  [WIDTH-1:0] d0, d1, d2,
              input  [1:0]       s,
              output [WIDTH-1:0] y);

  assign #1 y = s[1] ? d2 : (s[0] ? d1 : d0);
endmodule

module mux4 #(parameter WIDTH = 8)
             (input  [WIDTH-1:0] d0, d1, d2, d3,
              input  [1:0]       s,
              output reg [WIDTH-1:0] y);

   always @ (*)
      case(s)
         2'b00: y <= d0;
         2'b01: y <= d1;
         2'b10: y <= d2;
         2'b11: y <= d3;
      endcase
endmodule

mcp/controller_tb.v
module controller_tb;
    reg        clk, reset;
    reg  [5:0] op, funct;
    reg        zero;
    wire       pcen, memwrite, irwrite, regwrite;
    wire       alusrca, iord, memtoreg, regdst;
    wire [1:0] alusrcb, pcsrc;
    wire [2:0] alucontrol;
    reg [14:0] result, result_expected;
    reg [14:0] vectornum, errors;
    reg [38:0] testvector[6:0];

    controller dut(clk, reset,
                    op, funct,
                    zero, pcen,
                    memwrite, irwrite, regwrite,
                    alusrca, iord, memtoreg, regdst,
                    alusrcb, pcsrc,
                    alucontrol);

    always begin
      clk = 1; #10; clk = 0; #10;
    end

    initial begin
      $readmemh("controller.tv", testvector);
      vectornum = 0; errors = 0;
    end

    always @(posedge clk) begin
            op = testvector[vectornum][33:28];
            funct = testvector[vectornum][25:22];
            zero = testvector[vectornum][17];
            result_expected = testvector[vectornum][14:0];
    end

    always @(negedge clk) begin
        if (result !== result_expected) begin
            $display("Errors in vector %d", vectornum);
            $display(" Inputs: op = %b, funct = %b, zero = %b", op, funct, zero);
            $display(" Outputs: result = %h (%h expected)", result, result_expected);
            errors = errors + 1;
        end
        vectornum = vectornum + 1;
        if (vectornum === 7) begin
            $display("%d tests completed with %d error(s)",vectornum, errors);
            $finish;
        end
    end

    initial begin
        $dumpfile("alu.vcd");
        $dumpvars;
    end
endmodule

mcp/alu.vcd
$date
	Mon Jul 13 13:42:44 2020
$end
$version
	Icarus Verilog
$end
$timescale
	1s
$end
$scope module controller_tb $end
$var wire 3 ! alucontrol [2:0] $end
$var wire 1 " alusrca $end
$var wire 2 # alusrcb [1:0] $end
$var wire 1 $ iord $end
$var wire 1 % irwrite $end
$var wire 1 & memtoreg $end
$var wire 1 ' memwrite $end
$var wire 1 ( pcen $end
$var wire 2 ) pcsrc [1:0] $end
$var wire 1 * regdst $end
$var wire 1 + regwrite $end
$var reg 1 , clk $end
$var reg 15 - errors [14:0] $end
$var reg 6 . funct [5:0] $end
$var reg 6 / op [5:0] $end
$var reg 1 0 reset $end
$var reg 15 1 result [14:0] $end
$var reg 15 2 result_expected [14:0] $end
$var reg 15 3 vectornum [14:0] $end
$var reg 1 4 zero $end
$scope module dut $end
$var wire 3 5 alucontrol [2:0] $end
$var wire 1 " alusrca $end
$var wire 2 6 alusrcb [1:0] $end
$var wire 1 , clk $end
$var wire 6 7 funct [5:0] $end
$var wire 1 $ iord $end
$var wire 1 % irwrite $end
$var wire 1 & memtoreg $end
$var wire 1 ' memwrite $end
$var wire 6 8 op [5:0] $end
$var wire 1 ( pcen $end
$var wire 2 9 pcsrc [1:0] $end
$var wire 1 * regdst $end
$var wire 1 + regwrite $end
$var wire 1 0 reset $end
$var wire 1 4 zero $end
$var wire 1 : pcwrite $end
$var wire 1 ; branch $end
$var wire 2 < aluop [1:0] $end
$scope module ad $end
$var wire 6 = funct [5:0] $end
$var wire 2 > aluop [1:0] $end
$var reg 3 ? alucontrol [2:0] $end
$upscope $end
$scope module md $end
$var wire 1 " alusrca $end
$var wire 2 @ alusrcb [1:0] $end
$var wire 1 , clk $end
$var wire 1 $ iord $end
$var wire 1 % irwrite $end
$var wire 1 & memtoreg $end
$var wire 1 ' memwrite $end
$var wire 6 A op [5:0] $end
$var wire 2 B pcsrc [1:0] $end
$var wire 1 * regdst $end
$var wire 1 + regwrite $end
$var wire 1 0 reset $end
$var wire 1 : pcwrite $end
$var wire 1 ; branch $end
$var wire 2 C aluop [1:0] $end
$var reg 15 D controls [14:0] $end
$var reg 4 E nextstate [3:0] $end
$var reg 4 F state [3:0] $end
$upscope $end
$upscope $end
$upscope $end
$scope module mips $end
$var wire 32 G adr [31:0] $end
$var wire 1 H clk $end
$var wire 32 I readdata [31:0] $end
$var wire 1 J reset $end
$var wire 32 K writedata [31:0] $end
$var wire 1 L zero $end
$var wire 1 M regwrite $end
$var wire 1 N regdst $end
$var wire 2 O pcsrc [1:0] $end
$var wire 1 P pcen $end
$var wire 6 Q op [5:0] $end
$var wire 1 R memwrite $end
$var wire 1 S memtoreg $end
$var wire 1 T irwrite $end
$var wire 1 U iord $end
$var wire 6 V funct [5:0] $end
$var wire 2 W alusrcb [1:0] $end
$var wire 1 X alusrca $end
$var wire 3 Y alucontrol [2:0] $end
$scope module c $end
$var wire 1 H clk $end
$var wire 1 P pcen $end
$var wire 1 J reset $end
$var wire 1 L zero $end
$var wire 1 M regwrite $end
$var wire 1 N regdst $end
$var wire 1 Z pcwrite $end
$var wire 2 [ pcsrc [1:0] $end
$var wire 6 \ op [5:0] $end
$var wire 1 R memwrite $end
$var wire 1 S memtoreg $end
$var wire 1 T irwrite $end
$var wire 1 U iord $end
$var wire 6 ] funct [5:0] $end
$var wire 1 ^ branch $end
$var wire 2 _ alusrcb [1:0] $end
$var wire 1 X alusrca $end
$var wire 2 ` aluop [1:0] $end
$var wire 3 a alucontrol [2:0] $end
$scope module ad $end
$var wire 6 b funct [5:0] $end
$var wire 2 c aluop [1:0] $end
$var reg 3 d alucontrol [2:0] $end
$upscope $end
$scope module md $end
$var wire 1 H clk $end
$var wire 1 J reset $end
$var wire 1 M regwrite $end
$var wire 1 N regdst $end
$var wire 1 Z pcwrite $end
$var wire 2 e pcsrc [1:0] $end
$var wire 6 f op [5:0] $end
$var wire 1 R memwrite $end
$var wire 1 S memtoreg $end
$var wire 1 T irwrite $end
$var wire 1 U iord $end
$var wire 1 ^ branch $end
$var wire 2 g alusrcb [1:0] $end
$var wire 1 X alusrca $end
$var wire 2 h aluop [1:0] $end
$var reg 15 i controls [14:0] $end
$var reg 4 j nextstate [3:0] $end
$var reg 4 k state [3:0] $end
$upscope $end
$upscope $end
$scope module dp $end
$var wire 32 l adr [31:0] $end
$var wire 3 m alucontrol [2:0] $end
$var wire 1 X alusrca $end
$var wire 2 n alusrcb [1:0] $end
$var wire 1 H clk $end
$var wire 32 o instr [31:0] $end
$var wire 1 U iord $end
$var wire 1 T irwrite $end
$var wire 1 S memtoreg $end
$var wire 1 P pcen $end
$var wire 2 p pcsrc [1:0] $end
$var wire 32 q readdata [31:0] $end
$var wire 1 N regdst $end
$var wire 1 M regwrite $end
$var wire 1 J reset $end
$var wire 32 r writedata [31:0] $end
$var wire 1 L zero $end
$var wire 6 s op [5:0] $end
$var wire 6 t funct [5:0] $end
$upscope $end
$upscope $end
$scope module mux3 $end
$var wire 8 u d0 [7:0] $end
$var wire 8 v d1 [7:0] $end
$var wire 8 w d2 [7:0] $end
$var wire 2 x s [1:0] $end
$var wire 8 y y [7:0] $end
$upscope $end
$scope module mux4 $end
$var wire 8 z d0 [7:0] $end
$var wire 8 { d1 [7:0] $end
$var wire 8 | d2 [7:0] $end
$var wire 8 } d3 [7:0] $end
$var wire 2 ~ s [1:0] $end
$var reg 8 !" y [7:0] $end
$upscope $end
$enddefinitions $end
#0
$dumpvars
bx !"
bz ~
bz }
bz |
bz {
bz z
bx y
bz x
bz w
bz v
bz u
bz t
bz s
bz r
bz q
bx p
bz o
bx n
bx m
bz l
bx k
bx j
bx i
bx h
bx g
bz f
bx e
bx d
bx c
bz b
bx a
bx `
bx _
x^
bz ]
bz \
bx [
xZ
bx Y
xX
bx W
bz V
xU
xT
xS
xR
bz Q
xP
bx O
xN
xM
zL
bz K
zJ
bz I
zH
bz G
bx F
bx E
bx D
bx C
bx B
bx A
bx @
bx ?
bx >
bx =
bx <
x;
x:
bx 9
bx 8
bx 7
bx 6
bx 5
x4
b0 3
bx 2
bx 1
x0
bx /
bx .
b0 -
1,
x+
x*
bx )
x(
x'
x&
x%
x$
bx #
x"
bx !
$end
#1
bz y
#10
b1 3
0,
#20
b111000011110000 2
04
b1000 .
b1000 7
b1000 =
b100011 /
b100011 8
b100011 A
1,
#30
b10 3
b1 -
0,
#40
1,
#50
b11 3
b10 -
0,
#60
1,
#70
b100 3
b11 -
0,
#80
1,
#90
b101 3
b100 -
0,
#100
bx 2
x4
b0xxxx .
b0xxxx 7
b0xxxx =
bx /
bx 8
bx A
1,
#110
b110 3
0,
#120
1,
#130
b111 3
0,
