mcp/mipsmulti.v
module mips(input         clk, reset,
            output [31:0] adr, writedata,
            output        memwrite,
            input  [31:0] readdata);

  wire        zero, pcen, irwrite, regwrite;
  wire        alusrca, iord, memtoreg, regdst;
  wire [1:0]  alusrcb, pcsrc;
  wire [2:0]  alucontrol;
  wire [5:0]  op, funct;

  controller c(clk, reset, op, funct, zero,
               pcen, memwrite, irwrite, regwrite,
               alusrca, iord, memtoreg, regdst,
               alusrcb, pcsrc, alucontrol);


  datapath dp(clk, reset,
              pcen, irwrite, regwrite,
              alusrca, iord, memtoreg, regdst,
              alusrcb, pcsrc, alucontrol,
              op, funct, zero,
              adr, writedata, readdata);


endmodule

module controller(input        clk, reset,
                  input  [5:0] op, funct,
                  input        zero,
                  output       pcen, memwrite, irwrite, regwrite,
                  output       alusrca, iord, memtoreg, regdst,
                  output [1:0] alusrcb, pcsrc,
                  output [2:0] alucontrol);

  wire [1:0] aluop;
  wire       branch, pcwrite;

  // Main Decoder and ALU Decoder subunits.
  maindec md(clk, reset, op,
             pcwrite, memwrite, irwrite, regwrite,
             alusrca, branch, iord, memtoreg, regdst,
             alusrcb, pcsrc, aluop);
  aludec  ad(funct, aluop, alucontrol);

  assign pcen = (branch & zero) | pcwrite;
endmodule

module maindec(input        clk, reset,
               input  [5:0] op,
               output reg       pcwrite, memwrite, irwrite, regwrite,
               output reg     alusrca, branch, iord, memtoreg, regdst,
               output reg [1:0] alusrcb, pcsrc,
               output reg [1:0] aluop);

  // This is a moore machine.
  parameter   FETCH   = 4'b0000;  // State 0
  parameter   DECODE  = 4'b0001;  // State 1
  parameter   MEMADR  = 4'b0010;	// State 2
  parameter   MEMRD   = 4'b0011;	// State 3
  parameter   MEMWB   = 4'b0100;	// State 4
  parameter   MEMWR   = 4'b0101;	// State 5
  parameter   RTYPEEX = 4'b0110;	// State 6
  parameter   RTYPEWB = 4'b0111;	// State 7
  parameter   BEQEX   = 4'b1000;	// State 8
  parameter   ADDIEX  = 4'b1001;	// State 9
  parameter   ADDIWB  = 4'b1010;	// state 10
  parameter   JEX     = 4'b1011;	// State 11

  parameter   LW      = 6'b100011;	// Opcode for lw
  parameter   SW      = 6'b101011;	// Opcode for sw
  parameter   RTYPE   = 6'b000000;	// Opcode for R-type
  parameter   BEQ     = 6'b000100;	// Opcode for beq
  parameter   ADDI    = 6'b001000;	// Opcode for addi
  parameter   J       = 6'b000010;	// Opcode for j

  reg [3:0]  state, nextstate;
  reg [14:0] controls;

  // state register
  always @(posedge clk or posedge reset) begin
    if(reset) state <= FETCH;
    else state <= nextstate;
  end

  // next state logic
  always @ (*)
    case(state)
      FETCH:   nextstate <= DECODE;
      DECODE:  case(op)
                 LW:      nextstate <= MEMADR;
                 SW:      nextstate <= MEMADR;
                 RTYPE:   nextstate <= RTYPEEX;
                 BEQ:     nextstate <= BEQEX;
                 ADDI:    nextstate <= ADDIEX;
                 J:       nextstate <= JEX;
                 default: nextstate <= 4'bx; // should never happen
               endcase
      MEMADR: case(op)
                LW: nextstate <= MEMRD;
                SW: nextstate <= MEMWR;
                default: nextstate <= 4'bx; // should never happen
              endcase
      MEMRD: nextstate <= MEMWB;
      MEMWB: nextstate <= FETCH;
      MEMWR: nextstate <= FETCH;
      RTYPEEX: nextstate <= RTYPEWB;
      RTYPEWB: nextstate <= FETCH;
      BEQEX: nextstate <= FETCH;
      ADDIEX: nextstate <= ADDIWB;
      ADDIWB: nextstate <= FETCH;
      JEX: nextstate <= FETCH;
      default: nextstate <= 4'bx; // should never happen
    endcase

  // output logic

  always @ (*) begin
    case(state)
      FETCH:    controls <= 15'h5010;
      DECODE:   controls <= 15'h0030;
      MEMADR:   controls <= 15'h0420;
      MEMRD:    controls <= 15'h0100;
      MEMWB:    controls <= 15'h0880;
      MEMWR:    controls <= 15'h2100;
      RTYPEEX:  controls <= 15'h0402;
      RTYPEWB:  controls <= 15'h0840;
      BEQEX:    controls <= 15'h0605;
      ADDIEX:   controls <= 15'h0420;
      ADDIWB:   controls <= 15'h1000;
      JEX:      controls <= 15'h4008;
      default: controls <= 15'hxxxx; // should never happen
    endcase
    pcwrite <= controls[14];
    memwrite <= controls[13];
    irwrite <= controls[12];
    regwrite <= controls[11];
    alusrca <= controls[10];
    branch <= controls[9];
    iord <= controls[8];
    memtoreg <= controls[7];
    regdst <= controls[6];
    alusrcb <= controls[5:4];
    pcsrc <= controls[3:2];
    aluop <= controls[1:0];
  end


endmodule

module aludec(input  [5:0] funct,
              input  [1:0] aluop,
              output reg [2:0] alucontrol);

always@(*)
    case(aluop)
    2'b00:  alucontrol <= 3'b010; // add
    2'b01:  alucontrol <= 3'b110; // sub
    default: case(funct)
        6'b100000: alucontrol <= 3'b010; // add
        6'b100010: alucontrol <= 3'b110; // sub
        6'b100100: alucontrol <= 3'b000; // and
        6'b100101: alucontrol <= 3'b001; // or
        6'b101010: alucontrol <= 3'b111; // slt
        default:   alucontrol <= 3'bxxx; // ???
      endcase
    endcase
endmodule


module datapath(input          clk, reset,
                input          pcen, irwrite, regwrite,
                input          alusrca, iord, memtoreg, regdst,
                input   [1:0]  alusrcb, pcsrc,
                input   [2:0]  alucontrol,
                output  [5:0]  op, funct,
                output         zero,
                output  [31:0] adr,
                output  reg [31:0]writedata,
                input   [31:0] readdata);

//----------------  Wire-Reg box -----------------------
                wire [4:0]  writereg;
                wire [31:0] pcnext;
                reg  [31:0]  pc;
                reg  [31:0] instr, data;
                wire [31:0] srca, srcb;
                reg  [31:0] a;
                wire [31:0] aluresult;
                reg  [31:0] aluout;
                wire [31:0] signimm;
                wire [31:0] signimmsh;
                wire [31:0] wd3, rd1, rd2;
//---------------------------------------------------

  // Setting codes for control unit
  assign op = instr[31:26];
  assign funct = instr[5:0];

  //"Activate" program when reset is asserted
  always @ (*) begin
   if (reset) pc <= 0;
  end

 //Regfile logic
  regfile    regf(clk, regwrite, instr[25:21], instr[20:16], writereg, wd3, rd1, rd2);

  mux2 #(5)  RegDstMux(instr[20:16], instr[15:11], regdst, writereg);

  mux2 #(32) WD3Mux(aluout, data, memtoreg, wd3);

  //Adjusting some wires
  signext    se(instr[15:0], signimm);

  sl2        inmsl2(signimm, signimmsh);


  //ALU Logic
  mux2 #(32) SrcAmux(pc,a,alusrca,srca);

  mux4 #(32) SrcBmux(writedata, 32'b100, signimm, signimmsh, alusrcb, srcb);

  alu        alu(srca,srcb,alucontrol,aluresult,zero);

  //Saving ALU output
  always @ (posedge clk) begin
    aluout <= aluresult;
  end

  //Saving operands from register
  always @ (posedge clk) begin
    a <= rd1;
    writedata <= rd2;
  end

  //Setting Instr and Data. Always on posedge
  always @ (posedge clk) begin
   if(irwrite)  instr <=  readdata;
   data <= readdata;
  end

  //NextPC Logic
  mux3 #(32) Nextmux(aluresult, aluout, { pc[31:28], {instr[25:0], 2'b00} }, pcsrc, pcnext);

  mux2 #(32) PCadrMux(pc,aluout,iord,adr);

  //Going to next instruction
   always @ (posedge clk)begin
     if(pcen) pc <= pcnext;
   end

endmodule

//-------------------------Inner modules---------------------------------
              module mux3 #(parameter WIDTH = 8)
                           (input  [WIDTH-1:0] d0, d1, d2,
                            input  [1:0]       s,
                            output [WIDTH-1:0] y);

                assign #1 y = s[1] ? d2 : (s[0] ? d1 : d0);
              endmodule

              module mux4 #(parameter WIDTH = 8)
                           (input  [WIDTH-1:0] d0, d1, d2, d3,
                            input  [1:0]       s,
                            output reg [WIDTH-1:0] y);

                 always @ (*)
                    case(s)
                       2'b00: y <= d0;
                       2'b01: y <= d1;
                       2'b10: y <= d2;
                       2'b11: y <= d3;
                    endcase
              endmodule

              module mux2 # (parameter WIDTH = 8)
                            (input [WIDTH-1:0] d0, d1,
                            input s,
                            output [WIDTH-1:0] y);
                assign y = s? d1 : d0;
              endmodule

              module signext (input [15:0] a,
                              output [31:0] y);
              assign y = {{16{a[15]}}, a};
              endmodule

              module regfile(input          clk,
                             input          we3,
                             input   [4:0]  ra1, ra2, wa3,
                             input   [31:0] wd3,
                             output  [31:0] rd1, rd2);

                reg [31:0] rf[31:0];

                always @(posedge clk)
                  if (we3) rf[wa3] <= wd3;
                      assign rd1 = (ra1 != 0) ? rf[ra1] : 0;
                      assign rd2 = (ra2 != 0) ? rf[ra2] : 0;
              endmodule

              module sl2(input    [31:0]  a,
                          output  [31:0]  y);
                  // shift left by 2
                  assign y = {a[25:0], 2'b00};
              endmodule

// ---------------------------------------------------------------------

L5_files_OPMUX_update/ALU.v
module alu(a,b,aluop,result);
    input [31:0] a,b;
    input [3:0] aluop;
    output [31:0] result;
    output flag;

    always @(aluop) begin
        casex(aluop)
            
        endcase
    end

endmodule

mcp/controllertest_xx.v
module controller_tb;
    reg        clk, reset;
    reg  [5:0] op, funct;
    reg        zero;
    wire       pcen, memwrite, irwrite, regwrite;
    wire       alusrca, iord, memtoreg, regdst;
    wire [1:0] alusrcb, pcsrc;
    wire [2:0] alucontrol;
    reg [14:0] result, result_expected;
    reg [14:0] vectornum, errors;
    reg [38:0] testvector[24:0];

    controller dut(clk, reset,
                    op, funct,
                    zero, pcen,
                    memwrite, irwrite, regwrite,
                    alusrca, iord, memtoreg, regdst,
                    alusrcb, pcsrc,
                    alucontrol);

    always begin
      clk = 1; #10; clk = 0; #10; reset = 0;
    end

    initial begin
      $readmemh("controller.tv", testvector);
      //Vectornum is setted with -1 just to match with the correct clock cycle (after reset)
      vectornum = -1; errors = 0;
      reset = 1;
    end

    always @(posedge clk) begin
            op = testvector[vectornum][33:28];
            funct = testvector[vectornum][25:20];
            zero = testvector[vectornum][16];
            result_expected = testvector[vectornum][14:0];
    end

    always @(negedge clk) begin
        result <= {pcen, memwrite, irwrite, regwrite, alusrca, iord, memtoreg, regdst, alusrcb, pcsrc, alucontrol};
        if(vectornum) begin
          if (result !== result_expected) begin
              $display("\nErrors in vector %d", vectornum);
              $display(" Inputs: op = %b, funct = %b, zero = %b", op, funct, zero);
              $display(" Outputs: result = %h (%h expected)", result, result_expected);
              errors = errors + 1;
          end
        end
        vectornum = vectornum + 1;
        if (vectornum === 25) begin
            $display("%d tests (7 instructions) completed with %d error(s)",vectornum, errors);
            $finish;
        end
    end

    initial begin
        $dumpfile("controllertest.vcd");
        $dumpvars;
    end
endmodule

mcp/controllertest.vcd
$date
	Sun Jul 19 22:31:07 2020
$end
$version
	Icarus Verilog
$end
$timescale
	1s
$end
$scope module controller_tb $end
$var wire 3 ! alucontrol [2:0] $end
$var wire 1 " alusrca $end
$var wire 2 # alusrcb [1:0] $end
$var wire 1 $ iord $end
$var wire 1 % irwrite $end
$var wire 1 & memtoreg $end
$var wire 1 ' memwrite $end
$var wire 1 ( pcen $end
$var wire 2 ) pcsrc [1:0] $end
$var wire 1 * regdst $end
$var wire 1 + regwrite $end
$var reg 1 , clk $end
$var reg 15 - errors [14:0] $end
$var reg 6 . funct [5:0] $end
$var reg 6 / op [5:0] $end
$var reg 1 0 reset $end
$var reg 15 1 result [14:0] $end
$var reg 15 2 result_expected [14:0] $end
$var reg 15 3 vectornum [14:0] $end
$var reg 1 4 zero $end
$scope module dut $end
$var wire 3 5 alucontrol [2:0] $end
$var wire 2 6 aluop [1:0] $end
$var wire 1 " alusrca $end
$var wire 2 7 alusrcb [1:0] $end
$var wire 1 8 branch $end
$var wire 1 9 clk $end
$var wire 6 : funct [5:0] $end
$var wire 1 $ iord $end
$var wire 1 % irwrite $end
$var wire 1 & memtoreg $end
$var wire 1 ' memwrite $end
$var wire 6 ; op [5:0] $end
$var wire 1 ( pcen $end
$var wire 2 < pcsrc [1:0] $end
$var wire 1 = pcwrite $end
$var wire 1 * regdst $end
$var wire 1 + regwrite $end
$var wire 1 > reset $end
$var wire 1 ? zero $end
$scope module md $end
$var wire 1 9 clk $end
$var wire 6 @ op [5:0] $end
$var wire 1 > reset $end
$var reg 2 A aluop [1:0] $end
$var reg 1 B alusrca $end
$var reg 2 C alusrcb [1:0] $end
$var reg 1 D branch $end
$var reg 15 E controls [14:0] $end
$var reg 1 F iord $end
$var reg 1 G irwrite $end
$var reg 1 H memtoreg $end
$var reg 1 I memwrite $end
$var reg 4 J nextstate [3:0] $end
$var reg 2 K pcsrc [1:0] $end
$var reg 1 L pcwrite $end
$var reg 1 M regdst $end
$var reg 1 N regwrite $end
$var reg 4 O state [3:0] $end
$upscope $end
$scope module ad $end
$var wire 2 P aluop [1:0] $end
$var wire 6 Q funct [5:0] $end
$var reg 3 R alucontrol [2:0] $end
$upscope $end
$upscope $end
$upscope $end
$scope module mips $end
$var wire 32 S adr [31:0] $end
$var wire 3 T alucontrol [2:0] $end
$var wire 1 U alusrca $end
$var wire 2 V alusrcb [1:0] $end
$var wire 1 W clk $end
$var wire 6 X funct [5:0] $end
$var wire 1 Y iord $end
$var wire 1 Z irwrite $end
$var wire 1 [ memtoreg $end
$var wire 1 \ memwrite $end
$var wire 6 ] op [5:0] $end
$var wire 1 ^ pcen $end
$var wire 2 _ pcsrc [1:0] $end
$var wire 32 ` readdata [31:0] $end
$var wire 1 a regdst $end
$var wire 1 b regwrite $end
$var wire 1 c reset $end
$var wire 32 d writedata [31:0] $end
$var wire 1 e zero $end
$scope module c $end
$var wire 3 f alucontrol [2:0] $end
$var wire 2 g aluop [1:0] $end
$var wire 1 U alusrca $end
$var wire 2 h alusrcb [1:0] $end
$var wire 1 i branch $end
$var wire 1 W clk $end
$var wire 6 j funct [5:0] $end
$var wire 1 Y iord $end
$var wire 1 Z irwrite $end
$var wire 1 [ memtoreg $end
$var wire 1 \ memwrite $end
$var wire 6 k op [5:0] $end
$var wire 1 ^ pcen $end
$var wire 2 l pcsrc [1:0] $end
$var wire 1 m pcwrite $end
$var wire 1 a regdst $end
$var wire 1 b regwrite $end
$var wire 1 c reset $end
$var wire 1 e zero $end
$scope module md $end
$var wire 1 W clk $end
$var wire 6 n op [5:0] $end
$var wire 1 c reset $end
$var reg 2 o aluop [1:0] $end
$var reg 1 p alusrca $end
$var reg 2 q alusrcb [1:0] $end
$var reg 1 r branch $end
$var reg 15 s controls [14:0] $end
$var reg 1 t iord $end
$var reg 1 u irwrite $end
$var reg 1 v memtoreg $end
$var reg 1 w memwrite $end
$var reg 4 x nextstate [3:0] $end
$var reg 2 y pcsrc [1:0] $end
$var reg 1 z pcwrite $end
$var reg 1 { regdst $end
$var reg 1 | regwrite $end
$var reg 4 } state [3:0] $end
$upscope $end
$scope module ad $end
$var wire 2 ~ aluop [1:0] $end
$var wire 6 !" funct [5:0] $end
$var reg 3 "" alucontrol [2:0] $end
$upscope $end
$upscope $end
$upscope $end
$enddefinitions $end
#0
$dumpvars
bx ""
bz !"
bx ~
bx }
x|
x{
xz
bx y
bx x
xw
xv
xu
xt
bx s
xr
bx q
xp
bx o
bz n
xm
bx l
bz k
bz j
xi
bx h
bx g
bx f
ze
bz d
zc
xb
xa
bz `
bx _
x^
bz ]
x\
x[
xZ
xY
bz X
zW
bx V
xU
bx T
bz S
b10 R
bx Q
b0 P
b0 O
0N
0M
1L
b0 K
b1 J
0I
0H
1G
0F
b101000000010000 E
0D
b1 C
0B
b0 A
bx @
x?
1>
1=
b0 <
bx ;
bx :
19
08
b1 7
b0 6
b10 5
x4
b111111111111111 3
bx 2
bx 1
10
bx /
bx .
b0 -
1,
0+
0*
b0 )
1(
0'
0&
1%
0$
b1 #
0"
b10 !
$end
#10
b101000000100010 1
b0 3
0,
09
#20
0(
b11 C
b11 #
b11 7
0G
0%
0L
0=
b110000 E
b110 J
b1 O
b0 2
04
0?
b0 .
b0 :
b0 Q
b0 /
b0 ;
b0 @
1,
19
00
0>
#30
b1100010 1
b1 3
0,
09
#40
b10 A
b10 6
b10 P
b0 C
b0 #
b0 7
1B
1"
b10000000010 E
b111 J
b110 O
b1100010 2
b100000 .
b100000 :
b100000 Q
b100 /
b100 ;
b100 @
1,
19
#50
b10000000010 1
b10 3
0,
09
#60
b0 A
b0 6
b0 P
1M
1*
0B
0"
1N
1+
b100001000000 E
b0 J
b111 O
b10000000010 2
1,
19
#70
b100010000010 1
b11 3
0,
09
#80
1(
b1 C
b1 #
b1 7
0M
0*
0N
0+
1G
1%
1L
1=
b101000000010000 E
b1 J
b0 O
b100010000010 2
1,
19
#90
b101000000100010 1
b100 3
0,
09
#100
0(
b11 C
b11 #
b11 7
0G
0%
0L
0=
b110000 E
b1000 J
b1 O
b101000000100010 2
1,
19
#110
b1100010 1
b101 3
0,
09
#120
b110 R
b110 !
b110 5
b1 A
b1 6
b1 P
b1 K
b1 )
b1 <
b0 C
b0 #
b0 7
1D
18
1B
1"
b11000000101 E
b0 J
b1000 O
b1100010 2
1,
19
#130
b10000001110 1
b110 3
0,
09
#140
b10 R
b10 !
b10 5
1(
b0 A
b0 6
b0 P
b0 K
b0 )
b0 <
b1 C
b1 #
b1 7
0D
08
0B
0"
1G
1%
1L
1=
b101000000010000 E
b1 J
b0 O
b10000001110 2
1,
19
#150
b101000000100010 1
b111 3
0,
09
#160
0(
b11 C
b11 #
b11 7
0G
0%
0L
0=
b110000 E
b1000 J
b1 O
b101000000100010 2
14
1?
1,
19
#170
b1100010 1
b1000 3
0,
09
#180
b110 R
b110 !
b110 5
1(
b1 A
b1 6
b1 P
b1 K
b1 )
b1 <
b0 C
b0 #
b0 7
1D
18
1B
1"
b11000000101 E
b0 J
b1000 O
b1100010 2
1,
19
#190
b100010000001110 1
b1001 3
0,
09
#200
b10 R
b10 !
b10 5
b0 A
b0 6
b0 P
b0 K
b0 )
b0 <
b1 C
b1 #
b1 7
0D
08
0B
0"
1G
1%
1L
1=
b101000000010000 E
b1 J
b0 O
b100010000001110 2
1,
19
#210
b101000000100010 1
b1010 3
0,
09
#220
0(
b11 C
b11 #
b11 7
0G
0%
0L
0=
b110000 E
b1001 J
b1 O
b101000000100010 2
04
0?
b1000 /
b1000 ;
b1000 @
1,
19
#230
b1100010 1
b1011 3
0,
09
#240
b10 C
b10 #
b10 7
1B
1"
b10000100000 E
b1010 J
b1001 O
b1100010 2
1,
19
#250
b10001000010 1
b1100 3
0,
09
#260
b0 C
b0 #
b0 7
0B
0"
1G
1%
b1000000000000 E
b0 J
b1010 O
b10001000010 2
1,
19
#270
b1000000000010 1
b1101 3
0,
09
#280
1(
b1 C
b1 #
b1 7
1L
1=
b101000000010000 E
b1 J
b0 O
b1000000000010 2
1,
19
#290
b101000000100010 1
b1110 3
0,
09
#300
0(
b11 C
b11 #
b11 7
0G
0%
0L
0=
b110000 E
b1011 J
b1 O
b101000000100010 2
b10 /
b10 ;
b10 @
1,
19
#310
b1100010 1
b1111 3
0,
09
#320
1(
b10 K
b10 )
b10 <
b0 C
b0 #
b0 7
1L
1=
b100000000001000 E
b0 J
b1011 O
b1100010 2
1,
19
#330
b100000000010010 1
b10000 3
0,
09
#340
b0 K
b0 )
b0 <
b1 C
b1 #
b1 7
1G
1%
b101000000010000 E
b1 J
b0 O
b100000000010010 2
1,
19
#350
b101000000100010 1
b10001 3
0,
09
#360
0(
b11 C
b11 #
b11 7
0G
0%
0L
0=
b110000 E
b10 J
b1 O
b101000000100010 2
b101011 /
b101011 ;
b101011 @
1,
19
#370
b1100010 1
b10010 3
0,
09
#380
b10 C
b10 #
b10 7
1B
1"
b10000100000 E
b101 J
b10 O
b1100010 2
1,
19
#390
b10001000010 1
b10011 3
0,
09
#400
b0 C
b0 #
b0 7
1F
1$
0B
0"
1I
1'
b10000100000000 E
b0 J
b101 O
b10001000010 2
1,
19
#410
b10001000000010 1
b10100 3
0,
09
#420
1(
b1 C
b1 #
b1 7
0F
0$
1G
1%
0I
0'
1L
1=
b101000000010000 E
b1 J
b0 O
b10001000000010 2
1,
19
#430
b101000000100010 1
b10101 3
0,
09
#440
0(
b11 C
b11 #
b11 7
0G
0%
0L
0=
b110000 E
b10 J
b1 O
b101000000100010 2
b100011 /
b100011 ;
b100011 @
1,
19
#450
b1100010 1
b10110 3
0,
09
#460
b10 C
b10 #
b10 7
1B
1"
b10000100000 E
b11 J
b10 O
b1100010 2
1,
19
#470
b10001000010 1
b10111 3
0,
09
#480
b0 C
b0 #
b0 7
1F
1$
0B
0"
b100000000 E
b100 J
b11 O
b10001000010 2
1,
19
#490
b1000000010 1
b11000 3
0,
09
#500
1H
1&
0F
0$
1N
1+
b100010000000 E
b0 J
b100 O
b1000000010 2
1,
19
#510
b100100000010 1
b11001 3
0,
09
