mcp/mipsmulti.v
//-------------------------------------------------------
// mipsmulti.s
// From David_Harris and Sarah_Harris book design
// Multicycle MIPS processor
//------------------------------------------------

module mips(input         clk, reset,
            output [31:0] adr, writedata,
            output        memwrite,
            input  [31:0] readdata);

  wire        zero, pcen, irwrite, regwrite;
  wire        alusrca, iord, memtoreg, regdst;
  wire [1:0]  alusrcb, pcsrc;
  wire [2:0]  alucontrol;
  wire [5:0]  op, funct;

  controller c(clk, reset, op, funct, zero,
               pcen, memwrite, irwrite, regwrite,
               alusrca, iord, memtoreg, regdst,
               alusrcb, pcsrc, alucontrol);
  datapath dp(clk, reset,
              pcen, irwrite, regwrite,
              alusrca, iord, memtoreg, regdst,
              alusrcb, pcsrc, alucontrol,
              op, funct, zero,
              adr, writedata, readdata);
endmodule

module controller(input        clk, reset,
                  input  [5:0] op, funct,
                  input        zero,
                  output       pcen, memwrite, irwrite, regwrite,
                  output       alusrca, iord, memtoreg, regdst,
                  output [1:0] alusrcb, pcsrc,
                  output [2:0] alucontrol);

  wire [1:0] aluop;
  wire       branch, pcwrite;

  // Main Decoder and ALU Decoder subunits.
  maindec md(clk, reset, op,
             pcwrite, memwrite, irwrite, regwrite,
             alusrca, branch, iord, memtoreg, regdst,
             alusrcb, pcsrc, aluop);
  aludec  ad(funct, aluop, alucontrol);

  assign pcen = (branch & zero) | pcwrite;
endmodule

module maindec(input        clk, reset,
               input  [5:0] op,
               output       pcwrite, memwrite, irwrite, regwrite,
               output       alusrca, branch, iord, memtoreg, regdst,
               output [1:0] alusrcb, pcsrc,
               output [1:0] aluop);

  // This is a moore machine.
  parameter   FETCH   = 4'b0000; // State 0
  parameter   DECODE  = 4'b0001; // State 1
  parameter   MEMADR  = 4'b0010;	// State 2
  parameter   MEMRD   = 4'b0011;	// State 3
  parameter   MEMWB   = 4'b0100;	// State 4
  parameter   MEMWR   = 4'b0101;	// State 5
  parameter   RTYPEEX = 4'b0110;	// State 6
  parameter   RTYPEWB = 4'b0111;	// State 7
  parameter   BEQEX   = 4'b1000;	// State 8
  parameter   ADDIEX  = 4'b1001;	// State 9
  parameter   ADDIWB  = 4'b1010;	// state 10
  parameter   JEX     = 4'b1011;	// State 11

  parameter   LW      = 6'b100011;	// Opcode for lw
  parameter   SW      = 6'b101011;	// Opcode for sw
  parameter   RTYPE   = 6'b000000;	// Opcode for R-type
  parameter   BEQ     = 6'b000100;	// Opcode for beq
  parameter   ADDI    = 6'b001000;	// Opcode for addi
  parameter   J       = 6'b000010;	// Opcode for j

  reg [3:0]  state, nextstate;
  reg [14:0] controls;

  // state register
  always @(posedge clk or posedge reset) begin
    if(reset) state <= FETCH;
    else state <= nextstate;
  end

  // next state logic
  always @ (*)
    case(state)
      FETCH:   nextstate <= DECODE;
      DECODE:  case(op)
                 LW:      nextstate <= MEMADR;
                 SW:      nextstate <= MEMADR;
                 RTYPE:   nextstate <= RTYPEEX;
                 BEQ:     nextstate <= BEQEX;
                 ADDI:    nextstate <= ADDIEX;
                 J:       nextstate <= JEX;
                 default: nextstate <= 4'bx; // should never happen
               endcase
      MEMADR: case(op)
                LW: nextstate <= MEMRD;
                SW: nextstate <= MEMWR;
                default: nextstate <= 4'bx; // should never happen
              endcase
      MEMRD: nextstate <= MEMWB;
      MEMWB: nextstate <= FETCH;
      MEMWR: nextstate <= FETCH;
      RTYPEEX: nextstate <= RTYPEWB;
      RTYPEWB: nextstate <= FETCH;
      BEQEX: nextstate <= FETCH;
      ADDIEX: nextstate <= ADDIWB;
      ADDIWB: nextstate <= FETCH;
      JEX: nextstate <= FETCH;
      default: nextstate <= 4'bx; // should never happen
    endcase

  // output logic
  assign {pcwrite, memwrite, irwrite, regwrite,
          alusrca, branch, iord, memtoreg, regdst,
          alusrcb, pcsrc, aluop} = controls;

  always @ (*) begin
    case(state)
      FETCH:    controls <= 15'h5010;
      DECODE:   controls <= 15'h0030;
      MEMADR:   controls <= 15'h0420;
      MEMRD:    controls <= 15'h0100;
      MEMWB:    controls <= 15'h0880;
      MEMWR:    controls <= 15'h2100;
      RTYPEEX:  controls <= 15'h0402;
      RTYPEWB:  controls <= 15'h0840;
      BEQEX:    controls <= 15'h0605;
      ADDIEX:   controls <= 15'h0420;
      ADDIWB:   controls <= 15'h1000;
      JEX:      controls <= 15'h4008;
      default: controls <= 15'hxxxx; // should never happen
    endcase
  end
endmodule

module aludec(input  [5:0] funct,
              input  [1:0] aluop,
              output reg [2:0] alucontrol);

always@(*)
    case(aluop)
    2'b00:  alucontrol <= 3'b010; // add
    2'b01:  alucontrol <= 3'b110; // sub
    default: case(funct)
        6'b100000: alucontrol <= 3'b010; // add
        6'b100010: alucontrol <= 3'b110; // sub
        6'b100100: alucontrol <= 3'b000; // and
        6'b100101: alucontrol <= 3'b001; // or
        6'b101010: alucontrol <= 3'b111; // slt
        default:   alucontrol <= 3'bxxx; // ???
      endcase
    endcase
endmodule




// Complete the datapath module below for Lab 11.
// You do not need to complete this module for Lab 10

// The datapath unit is a structural verilog module.  That is,
// it is composed of instances of its sub-modules.  For example,
// the instruction register is instantiated as a 32-bit flopenr.
// The other submodules are likewise instantiated.

module datapath(input         clk, reset,
                input         pcen, irwrite, regwrite,
                input         alusrca, iord, memtoreg, regdst,
                input  [1:0]  alusrcb, pcsrc,
                input  [2:0]  alucontrol,
                output [5:0]  op, funct,
                output        zero,
                output [31:0] adr, writedata,
                input  [31:0] readdata);

  // Below are the internal signals of the datapath module.

  wire [4:0]  writereg;
  wire [31:0] pcnext, pc;
  wire [31:0] instr, data, srca, srcb;
  wire [31:0] a;
  wire [31:0] aluresult, aluout;
  wire [31:0] signimm;   // the sign-extended immediate
  wire [31:0] signimmsh;	// the sign-extended immediate shifted left by 2
  wire [31:0] wd3, rd1, rd2;

  // op and funct fields to controller
  assign op = instr[31:26];
  assign funct = instr[5:0];

  // Your datapath hardware goes below.  Instantiate each of the submodules
  // that you need.  Remember that alu's, mux's and various other
  // versions of parameterizable modules are available in mipsparts.sv
  // from Lab 9. You'll likely want to include this verilog file in your
  // simulation.

  // We've included parameterizable 3:1 and 4:1 muxes below for your use.

  // Remember to give your instantiated modules applicable names
  // such as pcreg (PC register), wdmux (Write Data Mux), etc.
  // so it's easier to understand.

  // ADD CODE HERE

  // datapath

endmodule


module mux3 #(parameter WIDTH = 8)
             (input  [WIDTH-1:0] d0, d1, d2,
              input  [1:0]       s,
              output [WIDTH-1:0] y);

  assign #1 y = s[1] ? d2 : (s[0] ? d1 : d0);
endmodule

module mux4 #(parameter WIDTH = 8)
             (input  [WIDTH-1:0] d0, d1, d2, d3,
              input  [1:0]       s,
              output reg [WIDTH-1:0] y);

   always @ (*)
      case(s)
         2'b00: y <= d0;
         2'b01: y <= d1;
         2'b10: y <= d2;
         2'b11: y <= d3;
      endcase
endmodule

mcp/controller_tb.v
module controller_tb;
    reg        clk, reset;
    reg  [5:0] op, funct;
    reg        zero;
    wire       pcen, memwrite, irwrite, regwrite;
    wire       alusrca, iord, memtoreg, regdst;
    wire [1:0] alusrcb, pcsrc;
    wire [2:0] alucontrol;
    reg [14:0] result, result_expected;
    reg [14:0] vectornum, errors;
    reg [38:0] testvector[6:0];

    assign {pcen, memwrite, irwrite, regwrite, alusrca, iord, memtoreg, regdst, alusrcb, pcsrc, alucontrol} = result;

    controller dut(clk, reset,
                    op, funct,
                    zero, pcen,
                    memwrite, irwrite, regwrite,
                    alusrca, iord, memtoreg, regdst,
                    alusrcb, pcsrc,
                    alucontrol);

    always begin
      clk = 1; #10; clk = 0; #10; reset = 0;
    end

    initial begin
      $readmemh("controller.tv", testvector);
      vectornum = 0; errors = 0;
      reset = 1;
    end

    always @(posedge clk) begin
            op = testvector[vectornum][33:28];
            funct = testvector[vectornum][25:20];
            zero = testvector[vectornum][15];
            result_expected = testvector[vectornum][14:0];
    end

    always @(negedge clk) begin
        // $display(pcen);
        // $display(memwrite);
        // $display(irwrite);
        // $display(regwrite);
        // $display(alusrca);
        // $display(iord);
        // $display(memtoreg);
        // $display(regdst);
        // $display(alusrcb);
        // $display(pcsrc);
        $display(result[14:0]);
        $display("%b, %b",op, funct);

        if (result !== result_expected) begin
            $display("Errors in vector %d", vectornum);
            $display(" Inputs: op = %b, funct = %b, zero = %b", op, funct, zero);
            $display(" Outputs: result = %h (%h expected)", result, result_expected);
            errors = errors + 1;
        end
        vectornum = vectornum + 1;
        if (vectornum === 7) begin
            $display("%d tests completed with %d error(s)",vectornum, errors);
            $finish;
        end
    end

    initial begin
        $dumpfile("mcp.vcd");
        $dumpvars;
    end
endmodule

mcp/mcp.vcd
$date
	Mon Jul 13 13:17:12 2020
$end
$version
	Icarus Verilog
$end
$timescale
	1s
$end
$scope module controller_tb $end
$var wire 3 ! alucontrol [2:0] $end
$var wire 1 " alusrca $end
$var wire 2 # alusrcb [1:0] $end
$var wire 1 $ iord $end
$var wire 1 % irwrite $end
$var wire 1 & memtoreg $end
$var wire 1 ' memwrite $end
$var wire 1 ( pcen $end
$var wire 2 ) pcsrc [1:0] $end
$var wire 1 * regdst $end
$var wire 1 + regwrite $end
$var reg 1 , clk $end
$var reg 15 - errors [14:0] $end
$var reg 6 . funct [5:0] $end
$var reg 6 / op [5:0] $end
$var reg 1 0 reset $end
$var reg 15 1 result [14:0] $end
$var reg 15 2 result_expected [14:0] $end
$var reg 15 3 vectornum [14:0] $end
$var reg 1 4 zero $end
$scope module dut $end
$var wire 3 5 alucontrol [2:0] $end
$var wire 2 6 aluop [1:0] $end
$var wire 1 " alusrca $end
$var wire 2 7 alusrcb [1:0] $end
$var wire 1 8 branch $end
$var wire 1 9 clk $end
$var wire 6 : funct [5:0] $end
$var wire 1 $ iord $end
$var wire 1 % irwrite $end
$var wire 1 & memtoreg $end
$var wire 1 ' memwrite $end
$var wire 6 ; op [5:0] $end
$var wire 1 ( pcen $end
$var wire 2 < pcsrc [1:0] $end
$var wire 1 = pcwrite $end
$var wire 1 * regdst $end
$var wire 1 + regwrite $end
$var wire 1 > reset $end
$var wire 1 ? zero $end
$scope module md $end
$var wire 2 @ aluop [1:0] $end
$var wire 1 " alusrca $end
$var wire 2 A alusrcb [1:0] $end
$var wire 1 8 branch $end
$var wire 1 9 clk $end
$var wire 1 $ iord $end
$var wire 1 % irwrite $end
$var wire 1 & memtoreg $end
$var wire 1 ' memwrite $end
$var wire 6 B op [5:0] $end
$var wire 2 C pcsrc [1:0] $end
$var wire 1 = pcwrite $end
$var wire 1 * regdst $end
$var wire 1 + regwrite $end
$var wire 1 > reset $end
$var reg 15 D controls [14:0] $end
$var reg 4 E nextstate [3:0] $end
$var reg 4 F state [3:0] $end
$upscope $end
$scope module ad $end
$var wire 2 G aluop [1:0] $end
$var wire 6 H funct [5:0] $end
$var reg 3 I alucontrol [2:0] $end
$upscope $end
$upscope $end
$upscope $end
$scope module mips $end
$var wire 32 J adr [31:0] $end
$var wire 3 K alucontrol [2:0] $end
$var wire 1 L alusrca $end
$var wire 2 M alusrcb [1:0] $end
$var wire 1 N clk $end
$var wire 6 O funct [5:0] $end
$var wire 1 P iord $end
$var wire 1 Q irwrite $end
$var wire 1 R memtoreg $end
$var wire 1 S memwrite $end
$var wire 6 T op [5:0] $end
$var wire 1 U pcen $end
$var wire 2 V pcsrc [1:0] $end
$var wire 32 W readdata [31:0] $end
$var wire 1 X regdst $end
$var wire 1 Y regwrite $end
$var wire 1 Z reset $end
$var wire 32 [ writedata [31:0] $end
$var wire 1 \ zero $end
$scope module c $end
$var wire 3 ] alucontrol [2:0] $end
$var wire 2 ^ aluop [1:0] $end
$var wire 1 L alusrca $end
$var wire 2 _ alusrcb [1:0] $end
$var wire 1 ` branch $end
$var wire 1 N clk $end
$var wire 6 a funct [5:0] $end
$var wire 1 P iord $end
$var wire 1 Q irwrite $end
$var wire 1 R memtoreg $end
$var wire 1 S memwrite $end
$var wire 6 b op [5:0] $end
$var wire 1 U pcen $end
$var wire 2 c pcsrc [1:0] $end
$var wire 1 d pcwrite $end
$var wire 1 X regdst $end
$var wire 1 Y regwrite $end
$var wire 1 Z reset $end
$var wire 1 \ zero $end
$scope module md $end
$var wire 2 e aluop [1:0] $end
$var wire 1 L alusrca $end
$var wire 2 f alusrcb [1:0] $end
$var wire 1 ` branch $end
$var wire 1 N clk $end
$var wire 1 P iord $end
$var wire 1 Q irwrite $end
$var wire 1 R memtoreg $end
$var wire 1 S memwrite $end
$var wire 6 g op [5:0] $end
$var wire 2 h pcsrc [1:0] $end
$var wire 1 d pcwrite $end
$var wire 1 X regdst $end
$var wire 1 Y regwrite $end
$var wire 1 Z reset $end
$var reg 15 i controls [14:0] $end
$var reg 4 j nextstate [3:0] $end
$var reg 4 k state [3:0] $end
$upscope $end
$scope module ad $end
$var wire 2 l aluop [1:0] $end
$var wire 6 m funct [5:0] $end
$var reg 3 n alucontrol [2:0] $end
$upscope $end
$upscope $end
$scope module dp $end
$var wire 32 o adr [31:0] $end
$var wire 3 p alucontrol [2:0] $end
$var wire 1 L alusrca $end
$var wire 2 q alusrcb [1:0] $end
$var wire 1 N clk $end
$var wire 6 r funct [5:0] $end
$var wire 32 s instr [31:0] $end
$var wire 1 P iord $end
$var wire 1 Q irwrite $end
$var wire 1 R memtoreg $end
$var wire 6 t op [5:0] $end
$var wire 1 U pcen $end
$var wire 2 u pcsrc [1:0] $end
$var wire 32 v readdata [31:0] $end
$var wire 1 X regdst $end
$var wire 1 Y regwrite $end
$var wire 1 Z reset $end
$var wire 32 w writedata [31:0] $end
$var wire 1 \ zero $end
$upscope $end
$upscope $end
$scope module mux3 $end
$var wire 8 x d0 [7:0] $end
$var wire 8 y d1 [7:0] $end
$var wire 8 z d2 [7:0] $end
$var wire 2 { s [1:0] $end
$var wire 8 | y [7:0] $end
$upscope $end
$scope module mux4 $end
$var wire 8 } d0 [7:0] $end
$var wire 8 ~ d1 [7:0] $end
$var wire 8 !" d2 [7:0] $end
$var wire 8 "" d3 [7:0] $end
$var wire 2 #" s [1:0] $end
$var reg 8 $" y [7:0] $end
$upscope $end
$enddefinitions $end
#0
$dumpvars
bx $"
bz #"
bz ""
bz !"
bz ~
bz }
bz |
bz {
bz z
bz y
bz x
bz w
bz v
bx u
bz t
bz s
bz r
bx q
bx p
bz o
bx n
bz m
bx l
bx k
bx j
bx i
bx h
bz g
bx f
bx e
xd
bx c
bz b
bz a
x`
bx _
bx ^
bx ]
z\
bz [
zZ
xY
xX
bz W
bx V
xU
bz T
xS
xR
xQ
xP
bz O
zN
bx M
xL
bx K
bz J
b10 I
bx H
b0 G
b0 F
b1 E
b101000000010000 D
bx C
bx B
bx A
b0 @
x?
1>
1=
bx <
bx ;
bx :
19
08
bx 7
b0 6
bx 5
x4
b0 3
bx 2
bx 1
10
bx /
bx .
b0 -
1,
x+
x*
bx )
x(
x'
x&
x%
x$
bx #
x"
bx !
$end
#1
bz |
#10
b1 3
0,
09
#20
0=
b110000 D
b110 E
b1 F
b110000 2
04
0?
b100000 .
b100000 :
b100000 H
b0 /
b0 ;
b0 B
1,
19
00
0>
#30
b10 3
b1 -
0,
09
#40
b10 6
b10 @
b10 G
b10000000010 D
b111 E
b110 F
b10000000010 2
1,
19
#50
b11 3
b10 -
0,
09
#60
b0 6
b0 @
b0 G
b100001000000 D
b0 E
b111 F
b100001000000 2
1,
19
#70
b100 3
b11 -
0,
09
#80
1=
b101000000010000 D
b1 E
b0 F
bx 2
x4
x?
bx .
bx :
bx H
bx /
bx ;
bx B
1,
19
#90
b101 3
0,
09
#100
0=
b110000 D
bx E
b1 F
1,
19
#110
b110 3
0,
09
#120
bx I
x=
x8
bx 6
bx @
bx G
bx D
bx F
1,
19
#130
b111 3
0,
09
