Code/arithmetic_part/add/add.v
module add(a, b, add_result);
    input   [31:0] a,b;
    output  [31:0] add_result;

    assign add_result = a + b;
endmodule

Code/arithmetic_part/add/add_tb.v
module add_tb();
    reg   [31:0] a,b;
    wire  [31:0] add_result;

    add add_(a, b, add_result);

    initial begin
        a = 32'b0; b = 32'b0;
        $monitor ("a = %h, b = %h, add_result  = %h", a, b, add_result);
        #64 $finish;
    end
    always #1 a = a + 67108864;
    always #2 b = b + 67108864;
    initial begin 
        $dumpfile("add_tb.vcd"); 
        $dumpvars;
    end
endmodule

Code/arithmetic_part/add/add_tb.vcd
$date
	Thu Jun 11 12:18:08 2020
$end
$version
	Icarus Verilog
$end
$timescale
	1s
$end
$scope module add_tb $end
$var wire 32 ! add_result [31:0] $end
$var reg 32 " a [31:0] $end
$var reg 32 # b [31:0] $end
$scope module add_ $end
$var wire 32 $ a [31:0] $end
$var wire 32 % b [31:0] $end
$var wire 32 & add_result [31:0] $end
$upscope $end
$upscope $end
$enddefinitions $end
#0
$dumpvars
b0 &
b0 %
b0 $
b0 #
b0 "
b0 !
$end
#1
b100000000000000000000000000 !
b100000000000000000000000000 &
b100000000000000000000000000 "
b100000000000000000000000000 $
#2
b1000000000000000000000000000 "
b1000000000000000000000000000 $
b1100000000000000000000000000 !
b1100000000000000000000000000 &
b100000000000000000000000000 #
b100000000000000000000000000 %
#3
b10000000000000000000000000000 !
b10000000000000000000000000000 &
b1100000000000000000000000000 "
b1100000000000000000000000000 $
#4
b10000000000000000000000000000 "
b10000000000000000000000000000 $
b11000000000000000000000000000 !
b11000000000000000000000000000 &
b1000000000000000000000000000 #
b1000000000000000000000000000 %
#5
b11100000000000000000000000000 !
b11100000000000000000000000000 &
b10100000000000000000000000000 "
b10100000000000000000000000000 $
#6
b11000000000000000000000000000 "
b11000000000000000000000000000 $
b100100000000000000000000000000 !
b100100000000000000000000000000 &
b1100000000000000000000000000 #
b1100000000000000000000000000 %
#7
b101000000000000000000000000000 !
b101000000000000000000000000000 &
b11100000000000000000000000000 "
b11100000000000000000000000000 $
#8
b100000000000000000000000000000 "
b100000000000000000000000000000 $
b110000000000000000000000000000 !
b110000000000000000000000000000 &
b10000000000000000000000000000 #
b10000000000000000000000000000 %
#9
b110100000000000000000000000000 !
b110100000000000000000000000000 &
b100100000000000000000000000000 "
b100100000000000000000000000000 $
#10
b101000000000000000000000000000 "
b101000000000000000000000000000 $
b111100000000000000000000000000 !
b111100000000000000000000000000 &
b10100000000000000000000000000 #
b10100000000000000000000000000 %
#11
b1000000000000000000000000000000 !
b1000000000000000000000000000000 &
b101100000000000000000000000000 "
b101100000000000000000000000000 $
#12
b110000000000000000000000000000 "
b110000000000000000000000000000 $
b1001000000000000000000000000000 !
b1001000000000000000000000000000 &
b11000000000000000000000000000 #
b11000000000000000000000000000 %
#13
b1001100000000000000000000000000 !
b1001100000000000000000000000000 &
b110100000000000000000000000000 "
b110100000000000000000000000000 $
#14
b111000000000000000000000000000 "
b111000000000000000000000000000 $
b1010100000000000000000000000000 !
b1010100000000000000000000000000 &
b11100000000000000000000000000 #
b11100000000000000000000000000 %
#15
b1011000000000000000000000000000 !
b1011000000000000000000000000000 &
b111100000000000000000000000000 "
b111100000000000000000000000000 $
#16
b1000000000000000000000000000000 "
b1000000000000000000000000000000 $
b1100000000000000000000000000000 !
b1100000000000000000000000000000 &
b100000000000000000000000000000 #
b100000000000000000000000000000 %
#17
b1100100000000000000000000000000 !
b1100100000000000000000000000000 &
b1000100000000000000000000000000 "
b1000100000000000000000000000000 $
#18
b1001000000000000000000000000000 "
b1001000000000000000000000000000 $
b1101100000000000000000000000000 !
b1101100000000000000000000000000 &
b100100000000000000000000000000 #
b100100000000000000000000000000 %
#19
b1110000000000000000000000000000 !
b1110000000000000000000000000000 &
b1001100000000000000000000000000 "
b1001100000000000000000000000000 $
#20
b1010000000000000000000000000000 "
b1010000000000000000000000000000 $
b1111000000000000000000000000000 !
b1111000000000000000000000000000 &
b101000000000000000000000000000 #
b101000000000000000000000000000 %
#21
b1111100000000000000000000000000 !
b1111100000000000000000000000000 &
b1010100000000000000000000000000 "
b1010100000000000000000000000000 $
#22
b1011000000000000000000000000000 "
b1011000000000000000000000000000 $
b10000100000000000000000000000000 !
b10000100000000000000000000000000 &
b101100000000000000000000000000 #
b101100000000000000000000000000 %
#23
b10001000000000000000000000000000 !
b10001000000000000000000000000000 &
b1011100000000000000000000000000 "
b1011100000000000000000000000000 $
#24
b1100000000000000000000000000000 "
b1100000000000000000000000000000 $
b10010000000000000000000000000000 !
b10010000000000000000000000000000 &
b110000000000000000000000000000 #
b110000000000000000000000000000 %
#25
b10010100000000000000000000000000 !
b10010100000000000000000000000000 &
b1100100000000000000000000000000 "
b1100100000000000000000000000000 $
#26
b1101000000000000000000000000000 "
b1101000000000000000000000000000 $
b10011100000000000000000000000000 !
b10011100000000000000000000000000 &
b110100000000000000000000000000 #
b110100000000000000000000000000 %
#27
b10100000000000000000000000000000 !
b10100000000000000000000000000000 &
b1101100000000000000000000000000 "
b1101100000000000000000000000000 $
#28
b1110000000000000000000000000000 "
b1110000000000000000000000000000 $
b10101000000000000000000000000000 !
b10101000000000000000000000000000 &
b111000000000000000000000000000 #
b111000000000000000000000000000 %
#29
b10101100000000000000000000000000 !
b10101100000000000000000000000000 &
b1110100000000000000000000000000 "
b1110100000000000000000000000000 $
#30
b1111000000000000000000000000000 "
b1111000000000000000000000000000 $
b10110100000000000000000000000000 !
b10110100000000000000000000000000 &
b111100000000000000000000000000 #
b111100000000000000000000000000 %
#31
b10111000000000000000000000000000 !
b10111000000000000000000000000000 &
b1111100000000000000000000000000 "
b1111100000000000000000000000000 $
#32
b10000000000000000000000000000000 "
b10000000000000000000000000000000 $
b11000000000000000000000000000000 !
b11000000000000000000000000000000 &
b1000000000000000000000000000000 #
b1000000000000000000000000000000 %
#33
b11000100000000000000000000000000 !
b11000100000000000000000000000000 &
b10000100000000000000000000000000 "
b10000100000000000000000000000000 $
#34
b10001000000000000000000000000000 "
b10001000000000000000000000000000 $
b11001100000000000000000000000000 !
b11001100000000000000000000000000 &
b1000100000000000000000000000000 #
b1000100000000000000000000000000 %
#35
b11010000000000000000000000000000 !
b11010000000000000000000000000000 &
b10001100000000000000000000000000 "
b10001100000000000000000000000000 $
#36
b10010000000000000000000000000000 "
b10010000000000000000000000000000 $
b11011000000000000000000000000000 !
b11011000000000000000000000000000 &
b1001000000000000000000000000000 #
b1001000000000000000000000000000 %
#37
b11011100000000000000000000000000 !
b11011100000000000000000000000000 &
b10010100000000000000000000000000 "
b10010100000000000000000000000000 $
#38
b10011000000000000000000000000000 "
b10011000000000000000000000000000 $
b11100100000000000000000000000000 !
b11100100000000000000000000000000 &
b1001100000000000000000000000000 #
b1001100000000000000000000000000 %
#39
b11101000000000000000000000000000 !
b11101000000000000000000000000000 &
b10011100000000000000000000000000 "
b10011100000000000000000000000000 $
#40
b10100000000000000000000000000000 "
b10100000000000000000000000000000 $
b11110000000000000000000000000000 !
b11110000000000000000000000000000 &
b1010000000000000000000000000000 #
b1010000000000000000000000000000 %
#41
b11110100000000000000000000000000 !
b11110100000000000000000000000000 &
b10100100000000000000000000000000 "
b10100100000000000000000000000000 $
#42
b10101000000000000000000000000000 "
b10101000000000000000000000000000 $
b11111100000000000000000000000000 !
b11111100000000000000000000000000 &
b1010100000000000000000000000000 #
b1010100000000000000000000000000 %
#43
b0 !
b0 &
b10101100000000000000000000000000 "
b10101100000000000000000000000000 $
#44
b10110000000000000000000000000000 "
b10110000000000000000000000000000 $
b1000000000000000000000000000 !
b1000000000000000000000000000 &
b1011000000000000000000000000000 #
b1011000000000000000000000000000 %
#45
b1100000000000000000000000000 !
b1100000000000000000000000000 &
b10110100000000000000000000000000 "
b10110100000000000000000000000000 $
#46
b10111000000000000000000000000000 "
b10111000000000000000000000000000 $
b10100000000000000000000000000 !
b10100000000000000000000000000 &
b1011100000000000000000000000000 #
b1011100000000000000000000000000 %
#47
b11000000000000000000000000000 !
b11000000000000000000000000000 &
b10111100000000000000000000000000 "
b10111100000000000000000000000000 $
#48
b11000000000000000000000000000000 "
b11000000000000000000000000000000 $
b100000000000000000000000000000 !
b100000000000000000000000000000 &
b1100000000000000000000000000000 #
b1100000000000000000000000000000 %
#49
b100100000000000000000000000000 !
b100100000000000000000000000000 &
b11000100000000000000000000000000 "
b11000100000000000000000000000000 $
#50
b11001000000000000000000000000000 "
b11001000000000000000000000000000 $
b101100000000000000000000000000 !
b101100000000000000000000000000 &
b1100100000000000000000000000000 #
b1100100000000000000000000000000 %
#51
b110000000000000000000000000000 !
b110000000000000000000000000000 &
b11001100000000000000000000000000 "
b11001100000000000000000000000000 $
#52
b11010000000000000000000000000000 "
b11010000000000000000000000000000 $
b111000000000000000000000000000 !
b111000000000000000000000000000 &
b1101000000000000000000000000000 #
b1101000000000000000000000000000 %
#53
b111100000000000000000000000000 !
b111100000000000000000000000000 &
b11010100000000000000000000000000 "
b11010100000000000000000000000000 $
#54
b11011000000000000000000000000000 "
b11011000000000000000000000000000 $
b1000100000000000000000000000000 !
b1000100000000000000000000000000 &
b1101100000000000000000000000000 #
b1101100000000000000000000000000 %
#55
b1001000000000000000000000000000 !
b1001000000000000000000000000000 &
b11011100000000000000000000000000 "
b11011100000000000000000000000000 $
#56
b11100000000000000000000000000000 "
b11100000000000000000000000000000 $
b1010000000000000000000000000000 !
b1010000000000000000000000000000 &
b1110000000000000000000000000000 #
b1110000000000000000000000000000 %
#57
b1010100000000000000000000000000 !
b1010100000000000000000000000000 &
b11100100000000000000000000000000 "
b11100100000000000000000000000000 $
#58
b11101000000000000000000000000000 "
b11101000000000000000000000000000 $
b1011100000000000000000000000000 !
b1011100000000000000000000000000 &
b1110100000000000000000000000000 #
b1110100000000000000000000000000 %
#59
b1100000000000000000000000000000 !
b1100000000000000000000000000000 &
b11101100000000000000000000000000 "
b11101100000000000000000000000000 $
#60
b11110000000000000000000000000000 "
b11110000000000000000000000000000 $
b1101000000000000000000000000000 !
b1101000000000000000000000000000 &
b1111000000000000000000000000000 #
b1111000000000000000000000000000 %
#61
b1101100000000000000000000000000 !
b1101100000000000000000000000000 &
b11110100000000000000000000000000 "
b11110100000000000000000000000000 $
#62
b11111000000000000000000000000000 "
b11111000000000000000000000000000 $
b1110100000000000000000000000000 !
b1110100000000000000000000000000 &
b1111100000000000000000000000000 #
b1111100000000000000000000000000 %
#63
b1111000000000000000000000000000 !
b1111000000000000000000000000000 &
b11111100000000000000000000000000 "
b11111100000000000000000000000000 $
#64
b0 "
b0 $
b10000000000000000000000000000000 !
b10000000000000000000000000000000 &
b10000000000000000000000000000000 #
b10000000000000000000000000000000 %
